Metadata-Version: 2.1
Name: example_package_evdev3
Version: 0.0.1
Summary: Sample pypi tutorial
Author: Evan Woods
Project-URL: Homepage, https://github.com/efwoods/pypi
Project-URL: Issues, https://github.com/efwoods/pypi/issues
Classifier: Programming Language :: Python :: 3
Classifier: License :: OSI Approved :: MIT License
Classifier: Operating System :: OS Independent
Requires-Python: >=3.8
License-File: LICENSE
